{
  "version": "7",
  "dialect": "postgresql",
  "entries": [
    {
      "idx": 0,
      "version": "7",
      "when": 1782971637737,
      "tag": "0000_init",
      "breakpoints": true
    },
    {
      "idx": 1,
      "version": "7",
      "when": 1782980385096,
      "tag": "0001_add_phone_encrypted",
      "breakpoints": true
    },
    {
      "idx": 2,
      "version": "7",
      "when": 1783063677455,
      "tag": "0002_registration_requested_access",
      "breakpoints": true
    },
    {
      "idx": 3,
      "version": "7",
      "when": 1783318696386,
      "tag": "0003_serious_vampiro",
      "breakpoints": true
    }
  ]
}